assignments/10knn1.py
assignments/11kmedoid.py
assignments/1ExploratoryDataAnalysis.py
assignments/2SimpleLinearRegression.py
assignments/3logisticregression.py
assignments/4NaiveBayes.py
assignments/5SupportVectorMachine.py
assignments/6DecisionTree.py
assignments/7RandomForest.py
assignments/8AdaptiveBoosting.py
assignments/9kmeans.py
assignments/__init__.py
melasanju-0.1.1.dist-info/METADATA
melasanju-0.1.1.dist-info/WHEEL
melasanju-0.1.1.dist-info/top_level.txt
melasanju-0.1.1.dist-info/RECORD
