Metadata-Version: 2.4
Name: melasanju
Version: 0.1.1
Summary: My 11 Python assignments packaged as a reusable library
Author-email: twilight <twilight1234d@gmail.com>
License: MIT
Requires-Python: >=3.8
